Metadata-Version: 2.1
Name: cloudmersive-ocr-api-client
Version: 2.1.2
Summary: ocrapi
Home-page: https://www.cloudmersive.com/ocr-api
Author-email: 
License: UNKNOWN
Keywords: Swagger,ocrapi
Platform: UNKNOWN
